<?xml version="1.0" encoding="UTF-8"?>
<mappings xmlns="http://dozer.sourceforge.net"  xmlns:xsi="http://www.w3.org/2001/XMLSchema-instance"
 xsi:schemaLocation="http://dozer.sourceforge.net http://dozer.sourceforge.net/schema/beanmapping.xsd">
	<configuration>
	    <custom-converters>
	        <converter type="com.mkren.building.service.converter.SmetaCustomConverter">
	            <class-a>com.mkren.building.entity.SmetaEntity</class-a>
        		<class-b>com.mkren.building.bean.SmetaBean</class-b>
	        </converter>
	        <converter type="com.mkren.building.service.converter.MagazineCustomConverter">
	            <class-a>com.mkren.building.entity.MagazineEntity</class-a>
        		<class-b>com.mkren.building.bean.MagazineBean</class-b>
	        </converter>
	        <converter type="com.mkren.building.service.converter.NewRecordConverter">
	            <class-a>com.mkren.building.entity.MagazineEntity</class-a>
        		<class-b>com.mkren.building.bean.NewRecordBean</class-b>
	        </converter>
	    </custom-converters>
	</configuration>
</mappings>